electrum_server
