Metadata-Version: 1.1
Name: reddcoin-electrum-server
Version: 0.9.2
Summary: Reddcoin Electrum server
Home-page: https://wallet.reddcoin.com
Author: Larry Ren
Author-email: ren@reddcoin.com
License: GNU Affero GPLv3
Download-URL: https://pypi.python.org/packages/source/l/reddcoin-electrum-server/reddcoin-electrum-server-0.9.2.tar.gz
Platform: All
Classifier: Environment :: Console
Classifier: Development Status :: 4 - Beta
Classifier: Intended Audience :: Developers
Classifier: Intended Audience :: System Administrators
Classifier: License :: OSI Approved :: GNU Affero General Public License v3
Classifier: Programming Language :: Python :: 2
Classifier: Programming Language :: Python :: 3
Classifier: Operating System :: OS Independent
Classifier: Topic :: Office/Business :: Financial
Classifier: Topic :: Software Development :: Libraries :: Python Modules
